cpp/sinkhorn.cpp
cpp/sinkhorn.h
uotod/__init__.py
uotod/colorboxes/__init__.py
uotod/loss/DetectionLoss.py
uotod/loss/GIoULoss.py
uotod/loss/IoULoss.py
uotod/loss/MultipleObjectiveLoss.py
uotod/loss/NegativeProbLoss.py
uotod/loss/SigmoidFocalLoss.py
uotod/loss/__init__.py
uotod/match/BalancedPOT.py
uotod/match/BalancedSinkhorn.py
uotod/match/ClosestPrediction.py
uotod/match/ClosestTarget.py
uotod/match/Hungarian.py
uotod/match/Min.py
uotod/match/SoftMin.py
uotod/match/UnbalancedPOT.py
uotod/match/UnbalancedSinkhorn.py
uotod/match/WeightedSum.py
uotod/match/_Compiled.py
uotod/match/_Match.py
uotod/match/_POT.py
uotod/match/_Sinkhorn.py
uotod/match/__init__.py
uotod/match/legacy/__init__.py
uotod/match/legacy/legacy_hungarian.py
uotod/match/legacy/legacy_ot.py
uotod/plot/__init__.py
uotod/plot/figure.py
uotod/plot/labels.py
uotod/plot/matrix.py
uotod/plot/params.py
uotod/sample/__init__.py
uotod/sample/elephants.py
uotod/sample/motorbike.py
uotod/utils/__init__.py
uotod/utils/conversions.py
uotod/utils/doc.py
uotod/utils/kwargs.py
uotod-0.3.post2.dist-info/LICENSE
uotod-0.3.post2.dist-info/METADATA
uotod-0.3.post2.dist-info/WHEEL
uotod-0.3.post2.dist-info/top_level.txt
uotod-0.3.post2.dist-info/RECORD
