Metadata-Version: 2.1
Name: uotod
Version: 0.3.post2
Summary: Unbalanced Optimal Transport for Object Detection
Author-email: Henri DE PLAEN <henri.deplaen@gmail.com>, Pierre-François DE PLAEN <pierre-francois.deplaen@esat.kuleuven.be>
License: GNU LESSER GENERAL PUBLIC LICENSE
Project-URL: Homepage, https://github.com/hdeplaen/uotod
Project-URL: GitHub, https://github.com/hdeplaen/uotod
Project-URL: Documentation, https://uotod.readthedocs.io/en/latest/
Project-URL: Issues, https://github.com/hdeplaen/uotod/issues
Project-URL: E-DUALITY, https://www.esat.kuleuven.be/stadius/E/
Project-URL: ESAT-STADIUS, https://www.esat.kuleuven.be/stadius/
Project-URL: ESAT-PSI, https://www.esat.kuleuven.be/psi/
Keywords: pytorch,machine learning
Classifier: Development Status :: 3 - Alpha
Classifier: Environment :: GPU :: NVIDIA CUDA
Classifier: Intended Audience :: Developers
Classifier: Intended Audience :: Education
Classifier: Intended Audience :: Science/Research
Classifier: Natural Language :: English
Classifier: Operating System :: MacOS
Classifier: Operating System :: Microsoft :: Windows
Classifier: Operating System :: OS Independent
Classifier: Operating System :: POSIX
Classifier: Operating System :: POSIX :: Linux
Classifier: Programming Language :: C++
Classifier: Programming Language :: Python :: 3
Classifier: Programming Language :: Python :: 3.10
Classifier: Programming Language :: Python :: 3.11
Classifier: Programming Language :: Python :: 3.12
Classifier: Programming Language :: Python :: 3.8
Classifier: Programming Language :: Python :: 3.9
Classifier: Topic :: Scientific/Engineering :: Artificial Intelligence
Classifier: Topic :: Scientific/Engineering :: Information Analysis
Classifier: Topic :: Scientific/Engineering :: Mathematics
Classifier: Topic :: Software Development :: Libraries :: Python Modules
Classifier: Topic :: Utilities
Requires-Python: >=3.8
License-File: LICENSE
Requires-Dist: matplotlib
Requires-Dist: numpy
Requires-Dist: pot
Requires-Dist: torch
Requires-Dist: torchvision
